{"acad_year":"2022/2023","preclusion":"All non-architecture students","description":"The objective of the program is to develop a level of competence in design skills and thinking. It involves the integration of technology with the natural environment, and urban context. Students address a generic brief by building upon it with emphasis in Urban, Environment, and/or Technological issues in a given site to demonstrate the acquisition of a level of competence in research, design thinking, operational skills and communication.","title":"Design 6","department":"Architecture","faculty":"College of Design and Engineering","prerequisite":"AR2101 Design 3 Grade 'C' or Grade “S”; AR2102 Design 4 Grade 'C'","module_credit":"8","module_code":"AR3102","prereq_tree":"","fulfill_requirements":["LA4701","LA4702","AR3411","AR4421"],"workload":[2,3,0,3,12]}