{"acad_year":"2022/2023","preclusion":"","description":"This module is designed to prepare student for the applied research project that must be submitted in Semester 4. This module builds on the knowledge obtained in AUD5115 Experimental Design and Statistics. Students will be asked to identify a client a research topic, and two supervisors, develop a research design and appropriate testing tools, make a class presentation to teaching staff and students and then submit a written proposal (max 5000 words) before obtaining ethics clearance and conducting a pilot study.","title":"Independent Studies in Audiology (Research project - part 1)","department":"Division of Graduate Medical Studies","faculty":"Yong Loo Lin Sch of Medicine","prerequisite":"AUD5115: Experimental Design and Statistics","module_credit":"8","module_code":"AUD5220","prereq_tree":"AUD5115","fulfill_requirements":["AUD5224"],"workload":[20,0,0,120,100]}