{"acad_year":"2022/2023","preclusion":"","description":"This class is intended to equip students to think about being future entrepreneurs through applicable knowledge to increase the success in launching and commercialising new start-up ideas. The class will utilise product development methodologies to build out product prototypes and roadmap. It will also provide practical ways to translate product requirements to an initial product launch and then ongoing enhancements. As part of business growth it will teach students how to systematically approach customer identification, acquisition and retention through direct or partnership channels and marketing/sales tools. It will also teach\nstudents how to continually build out a product roadmap through customer feedback.","title":"Entrepreneurship Business Development","department":"BIZ Dean's Office","faculty":"NUS Business School","prerequisite":"","module_credit":"4","module_code":"BMS5123S","prereq_tree":"","fulfill_requirements":[],"workload":[3,0,0,7,0]}