{"acad_year":"2022/2023","preclusion":"RE3801 ; EC2303; EC3303.","description":"This model introduces the science and art of building and using econometric models. It aims to equip business students to: (i) Understand and appreciate econometric analysis in economic and business reports; and (ii) Carry out estimation using least squares regression to support business analysis.","title":"Econometrics for Business I","department":"Strategy and Policy","faculty":"NUS Business School","prerequisite":"BSP1703 or BSP1707 or EC1101E or EC1301.","module_credit":"4","module_code":"BSE3703","prereq_tree":{"and":[],"or":["BSP1703","BSP1707","EC1101E","EC1301"]},"fulfill_requirements":["BSN4811A","BSS4003B"],"workload":[0,3,1,4,2]}