{"acad_year":"2022/2023","preclusion":"","description":"This module provides students with a comprehensive overview of aberrant cell growth control mechanisms in cancer. The major lecture topics will include introduction/history of cancer, virus and cancer, oncogenes, tumor suppressor genes, metastasis, tumor immunology, cancer stem cells, animal models, regulation of the cell cycle, cell death and cell signaling, telomeres, cancer genomics, development and cancer, metastasis. This module is an essential prerequisite for the Translational Cancer Research Module.","title":"Fundamentals of Cancer Biology","department":"NUS Medicine Dean's Office","faculty":"Yong Loo Lin Sch of Medicine","prerequisite":"","module_credit":"4","module_code":"CDM5101","prereq_tree":"","fulfill_requirements":["CDM5102"],"workload":[4,0,0,0,6]}