{"acad_year":"2022/2023","preclusion":"CS5439","description":"Software engineering processes need to include security considerations in the modern world. This module familiarizes students to security issues in different stages of the software life-cycle. At the end of the module, the students are expected to understand secure programming practices, be able to analyse and check for impact of malicious inputs in programs, and employ specific testing techniques which can help detect software vulnerabilities.","title":"Software Security","department":"Computer Science","faculty":"Computing","prerequisite":"CS3235 Computer Security and (CS2103 or its equivalent)","module_credit":"4","module_code":"CS4239","prereq_tree":{"and":["CS3235","CS2103"],"or":[]},"fulfill_requirements":[],"workload":[2,1,0,2,5]}