{"acad_year":"2022/2023","preclusion":"","description":"This module covers analytics tools, including machine learning, statistical modelling, and optimisation methods, to model, estimate, and manage quantitative risk. Hands-on implementation of these analytics tools in Python is an important component of this module.","title":"Analytics for Risk Management","department":"Analytics and Operations","faculty":"NUS Business School","prerequisite":"DAO2702 Programming for Business Analytics","module_credit":"4","module_code":"DBA3713","prereq_tree":"DAO2702","fulfill_requirements":[],"workload":[3,0,0,3,4]}