{"acad_year":"2022/2023","preclusion":"EC4301","description":"The module covers selected topics including economics of asymmetric information, auction and mechanism design, and matching and market design. The module will focus on delivering the economic insights and minimize the use of mathematical tools. Emphasis will be placed on main applications such as design of efficient and revenue‐maximizing auctions, design of stable school choice mechanisms, and design of efficient and optimal contracts.","title":"Applied Microeconomic Analysis","department":"Economics","faculty":"Arts and Social Science","prerequisite":"Completed 80 MCs, including 28 MCs in EC, with a minimum CAP of 3.20 or be on the Honours track. EC3101.","module_credit":"5","module_code":"EC4306","prereq_tree":"","fulfill_requirements":[],"workload":[0.0,3.0,0.0,2.0,7.5]}