{"acad_year":"2022/2023","preclusion":"","description":"When starting on their research, almost all students turn to the Internet, their supervisors or peers. With overwhelming information to deal with, how does a graduate student begin to systematically and comprehensively build a foundation of knowledge for their research based on credible sources?\n\nThis module aims to provide Engineering research students with the essential skills to conduct secondary research required for producing a good quality literature review and building the necessary knowledge base in their research area.\n\nStudents will be introduced to information literacy skills such as information search strategies, skills in evaluating information to determine authoritativeness and credibility, etc.","title":"Information Literacy Skills for Research","department":"CDE Dean's Office","faculty":"College of Design and Engineering","prerequisite":"","module_credit":"0","module_code":"EG5911R","prereq_tree":"","fulfill_requirements":[],"workload":[4,4,0,0,4]}