{"acad_year":"2022/2023","preclusion":"","description":"This module introduces students to factors that result in the loss of quality characteristics of plant and animal produce, and discusses how such losses can be minimized by proper and effective handling of the fresh produce, from farm to market. This module also covers the various aspects of post-harvest processes and the products derived from fresh produce. The roles of irradiation and packaging in extending the shelf-life of animal and plant produce are also discussed.","title":"Post Harvest Food Processing","department":"Food Science and Technology","faculty":"Science","prerequisite":"FST1101B","module_credit":"4","module_code":"FST2106","prereq_tree":"FST1101B","fulfill_requirements":["FST3104"],"workload":[2,1,3,2,2]}