{"acad_year":"2022/2023","preclusion":"","description":"This module will immerse students in a week-long intensive\nprogram as part of the Eureka Institute’s Merlion School, where\nstudents will conduct fieldwork on a self-directed learning\nactivity that focuses on enhancing their skills and competencies\nin Translational Medicine. Students will engage with\nTranslational Medicine researchers, policy makers, financers,\ntechnologists, and other scholars to explore the business,\nscientific, and regulatory aspects of Translational Medicine and\nbuilding their network of local and international collaborators.\nTopics include: ideation and design thinking, international\nnetworks, communication skills, presentation skills, enhancing\ncreativity in science, mentorship, and entrepreneurialism.","title":"Networking in International Translational\nMedicine","department":"Duke-NUS Dean's Office","faculty":"Duke-NUS Medical School","prerequisite":"Translational Medicine: From Unmet Need to Cure","module_credit":"6","module_code":"GMS5806","prereq_tree":"","fulfill_requirements":[],"workload":[50,0,0,20,5]}