{"acad_year":"2022/2023","preclusion":"","description":"This module provides an analytical treatment of the subject of facility layout and location. The layout design process consists of problem formulation, analysis of the problem, search for layout designs, selection of the preferred design, and specification of the layout design to be installed. It also considers the problem of locating one or several new facilities with respect to existing facilities. The objective considered is the minimization of a cost function of travel distances. Students will be required to do a project to apply the knowledge acquired from this module.","title":"Facility Layout And Location","department":"Industrial Systems Engineering and Management","faculty":"College of Design and Engineering","prerequisite":"","module_credit":"4","module_code":"IE5108","prereq_tree":"","fulfill_requirements":[],"workload":[3,0,0,3,4]}