{"acad_year":"2022/2023","preclusion":"","description":"This module teaches how to build Intelligent Systems that solve problems by reasoning using captured knowledge and data. Example applications include, question answering systems such as IBM Watson, personal assistants such as Amazon’s Alexa and Game-playing systems such as AlphaGo Zero.","title":"Intelligent Reasoning Systems","department":"Institute of Systems Science","faculty":"Institute of Systems Science","prerequisite":"","module_credit":"11","module_code":"ISY5001","prereq_tree":"","fulfill_requirements":["EBA5004G","EBA5004","ISY5007"],"workload":[6.5,6.5,2.0,6.5,1.0]}