{"acad_year":"2022/2023","preclusion":"","description":"In the digital era, in addition to concepts of marketing, students should also get exposed to latest tools and techniques that successful firms use to market technology products. It should be supported by numbers. Therefore, the course will additionally emphasize on: \n\n1. Which tools and techniques work better with the target segment? What are the upcoming trends? \n2. How are these decisions made anchoring back to numbers?","title":"Marketing of Technology Products in the Digital Era","department":"Industrial Systems Engineering and Management","faculty":"College of Design and Engineering","prerequisite":"","module_credit":"4","module_code":"MT5012","prereq_tree":"","fulfill_requirements":[],"workload":[3,0,0,0,7]}