{"acad_year":"2022/2023","preclusion":"","description":"“What is the meaning of the term “global citizenship”? What is its significance? And what are the obstacles and challenges to it? This module teaches academic writing through a critical exploration of the concept of global citizenship. Topics discussed include the historical doctrine of cosmopolitanism, the relevance of global citizenship as a moral, economic and cultural ideal as well as the institutionalization of global citizenship in the education curriculum. The module encourages students to reflect on the notion of global citizenship in the contemporary world, as well as their responsibilities as cosmopolitan citizens.”","title":"Cosmopolitanism and Global Citizenship","department":"NUS College Dean's Office","faculty":"NUS College","prerequisite":"","module_credit":"4","module_code":"NTW2001","prereq_tree":"","fulfill_requirements":[],"workload":[4,0,0,0,6]}