{"acad_year":"2022/2023","preclusion":"PR3117 Formulation & Technology II","description":"This module gives an introduction to solid dosage forms including tablets, capsules, powders and granules, as well as topical products and transdermal delivery. Formulations of emerging importance including biologics, polymers and biomaterials will be discussed. Fundamental knowledge of product quality and stability will be covered.","title":"Principles of Pharmaceutical Formulations II","department":"Pharmacy","faculty":"Science","prerequisite":"PHS1114 Principles of Pharmaceutical Formulations I","module_credit":"4","module_code":"PHS2117","prereq_tree":"PHS1114","fulfill_requirements":["PR4204"],"workload":[2,3,0,2,3]}