{"acad_year":"2022/2023","preclusion":"EE4214E, TEE4214","description":"This module introduces computer systems to students from the perspective of a programmer. Students learn about the computer systems, focusing on the hardware and operating systems, and how they impact the design, implementation, and performance of a programme. Topics covered include data representations, machine-level representations of C programmes, processor architecture, memory hierarchy, programme optimisation, linking, interrupts and signals, memory management, system-level I/O, and concurrency.","title":"Introduction to Computer Systems","department":"SCALE Dean's Office","faculty":"Cont and Lifelong Education","prerequisite":"TIC1002","module_credit":"4","module_code":"TIC2401","prereq_tree":"TIC1002","fulfill_requirements":["TIC3302","TIC4005"],"workload":[2,1,0,3,4]}