{"acad_year":"2022/2023","preclusion":"","description":"This module focuses on the close reading of dramatic texts in order to study the dynamic relationship between text & performance.  Through the examination of 4 major modern playwrights working in different historical, geographical and cultural contexts, this course will explore the development of modern drama in the 20th century, the significance of text as the basis of theatrical realization, the variety of staging possibilities engendered by the dramaturgy of the play-text, and the synergistic partnership of word and action in creating the huge variety of text-based theatre in the 20th century.","title":"Major Playwrights of the 20th Century","department":"English,Ling.andTheatre Studies","faculty":"Arts and Social Science","prerequisite":"TS1101E or EN1101E or GEM1003","module_credit":"4","module_code":"TS2239","prereq_tree":{"and":[],"or":["TS1101E","EN1101E","GEM1003"]},"fulfill_requirements":[],"workload":[3,0,0,3,4]}