{"acad_year":"2022/2023","preclusion":"","description":"What is portraiture? This class will equip students with means to conceptualise and develop photographic portraits over the semester. Students will make portraits through exercises using lighting and visual tropes and methods in portraiture. There will also be readings, screenings and visual analyses to enable them to consider different genres of portraiture, and their relationship to society, identity, visual representation and the self. This module will develop students’ artistic portfolios and will culminate in an exhibition at the end of the semester. Students are required to have working knowledge of camera handling","title":"Portraiture","department":"Yale-NUS College","faculty":"Yale-NUS College","prerequisite":"","module_credit":"5","module_code":"YHU4268","prereq_tree":"","fulfill_requirements":[],"workload":[0.0,0.0,0.0,8.0,4.5]}